langchain_mcp_client/__init__.py
langchain_mcp_client/__version__.py
langchain_mcp_client/chat.py
langchain_mcp_client/config_loader.py
langchain_mcp_client/mcp_tools.py
langchain_mcp_client/tests/__init__.py
langchain_mcp_client-0.3.0.dist-info/METADATA
langchain_mcp_client-0.3.0.dist-info/WHEEL
langchain_mcp_client-0.3.0.dist-info/entry_points.txt
langchain_mcp_client-0.3.0.dist-info/licenses/LICENSE
langchain_mcp_client-0.3.0.dist-info/RECORD
