Metadata-Version: 2.4
Name: langchain_mcp_client
Version: 0.3.0
Project-URL: Home, https://github.com/datalayer/langchain-mcp-client
Author-email: Datalayer <info@datalayer.io>
License: BSD 3-Clause License
License-File: LICENSE
Keywords: Jupyter
Classifier: Intended Audience :: Developers
Classifier: Intended Audience :: System Administrators
Classifier: License :: OSI Approved :: BSD License
Classifier: Programming Language :: Python
Classifier: Programming Language :: Python :: 3
Requires-Python: >=3.11
Requires-Dist: jsonschema-pydantic>=0.6
Requires-Dist: langchain-anthropic>=0.3.1
Requires-Dist: langchain-aws
Requires-Dist: langchain-github-copilot
Requires-Dist: langchain-groq>=0.2.3
Requires-Dist: langchain-openai>=0.3.0
Requires-Dist: langchain>=0.3.14
Requires-Dist: langgraph>=0.2.62
Requires-Dist: mcp>=1.2.0
Requires-Dist: pyjson5>=1.6.8
Requires-Dist: pympler>=1.1
Requires-Dist: python-dotenv>=1.0.1
Provides-Extra: lint
Requires-Dist: mdformat-gfm>=0.3.5; extra == 'lint'
Requires-Dist: mdformat>0.7; extra == 'lint'
Requires-Dist: ruff; extra == 'lint'
Provides-Extra: test
Requires-Dist: ipykernel; extra == 'test'
Requires-Dist: jupyter-server<3,>=1.6; extra == 'test'
Requires-Dist: pytest>=7.0; extra == 'test'
Provides-Extra: typing
Requires-Dist: mypy>=0.990; extra == 'typing'
